{
    "type": "ThemeStyle",
    "fontHeadlines": "fontPrimary",
    "h1": {
        "size": "6xl",
        "weight": "medium",
        "decoration": "none",
        "case": "none",
        "letterSpacing": "normal"
    },
    "h2": {
        "size": "5xl",
        "weight": "normal",
        "decoration": "none",
        "case": "none",
        "letterSpacing": "normal"
    },
    "h3": {
        "size": "3xl",
        "weight": "normal",
        "decoration": "none",
        "case": "none",
        "letterSpacing": "normal"
    },
    "h4": {
        "size": "2xl",
        "weight": "medium",
        "decoration": "none",
        "case": "none",
        "letterSpacing": "normal"
    },
    "h5": {
        "size": "xl",
        "weight": "medium",
        "decoration": "none",
        "case": "none",
        "letterSpacing": "normal"
    },
    "h6": {
        "size": "lg",
        "weight": "medium",
        "decoration": "none",
        "case": "none",
        "letterSpacing": "normal"
    },
    "main": "#EDEDED",
    "light": "#ffffff",
    "onLight": "#000000",
    "dark": "#303030",
    "onDark": "#ffffff",
    "primary": "#8f001a",
    "onPrimary": "#ffffff",
    "secondary": "#00629B40",
    "onSecondary": "#005180",
    "complementary": "#EDEDED",
    "onComplementary": "#000000bf",
    "complementaryAlt": "#00629B",
    "onComplementaryAlt": "#EAECEB",
    "buttonPrimary": {
        "weight": "normal",
        "case": "none",
        "letterSpacing": "normal",
        "borderRadius": "none",
        "horizontalPadding": 20,
        "verticalPadding": 10,
        "shadow": "none"
    },
    "buttonSecondary": {
        "weight": "normal",
        "case": "none",
        "letterSpacing": "normal",
        "borderRadius": "none",
        "borderStyle": "solid",
        "horizontalPadding": 20,
        "verticalPadding": 10,
        "shadow": "none"
    },
    "link": {
        "weight": "normal",
        "case": "none",
        "letterSpacing": "normal"
    },
    "fontBody": "fontSecondary"
}